{"cameraMode":{"drawMode":0,"name":"Shaded","section":"Shading Mode"},"sceneLighting":true,"audioPlay":false,"sceneViewState":{"showFog":true,"showMaterialUpdate":false,"showSkybox":true,"showFlares":true,"showImageEffects":true,"showParticleSystems":true},"in2DMode":false,"pivot":{"x":1212.6700439453125,"y":80.16999816894531,"z":370.6357421875},"rotation":{"x":-0.05315802991390228,"y":-0.9441513419151306,"z":0.26374155282974245,"w":-0.19029824435710908},"size":3.3444273471832277,"orthographic":false}